avinit/__init__.py
avinit-1.3.0.dist-info/LICENSE
avinit-1.3.0.dist-info/METADATA
avinit-1.3.0.dist-info/WHEEL
avinit-1.3.0.dist-info/top_level.txt
avinit-1.3.0.dist-info/RECORD
