Metadata-Version: 2.1
Name: avinit
Version: 1.3.0
Summary: Generate avatars using name initials
Home-page: https://github.com/CraveFood/avinit
Author: Sergio Oliveira
Author-email: seocam@seocam.com
License: UNKNOWN
Platform: UNKNOWN
Classifier: Development Status :: 5 - Production/Stable
Classifier: Environment :: Console
Classifier: Environment :: Web Environment
Classifier: Intended Audience :: Developers
Classifier: License :: OSI Approved :: GNU General Public License v3 (GPLv3)
Classifier: Programming Language :: Python
Provides-Extra: png
Requires-Dist: CairoSVG (<3.0.0,>=2.5.1) ; extra == 'png'
Requires-Dist: cairocffi (>=1.1.0) ; extra == 'png'
